UnityPyTypetreeCodegen/__init__.py
UnityPyTypetreeCodegen/__main__.py
unitypytypetreecodegen-0.0.14.dist-info/METADATA
unitypytypetreecodegen-0.0.14.dist-info/WHEEL
unitypytypetreecodegen-0.0.14.dist-info/entry_points.txt
unitypytypetreecodegen-0.0.14.dist-info/top_level.txt
unitypytypetreecodegen-0.0.14.dist-info/RECORD
