Metadata-Version: 2.4
Name: UnityPyTypetreeCodegen
Version: 0.0.14
Summary: Unity Typetree to Python Module code generator
Home-page: https://github.com/mos9527/UnityPyTypetreeCodegen
Author: greats3an
Author-email: greats3an@gmail.com
Classifier: Programming Language :: Python :: 3
Classifier: License :: OSI Approved :: Apache Software License
Classifier: Operating System :: OS Independent
Requires-Python: >=3.10
Requires-Dist: TypeTreeGeneratorAPIEx>=0.0.9
Requires-Dist: UnityPy>=1.21
Dynamic: author
Dynamic: author-email
Dynamic: classifier
Dynamic: description
Dynamic: description-content-type
Dynamic: home-page
Dynamic: requires-dist
Dynamic: requires-python
Dynamic: summary
